{"cameraMode":{"drawMode":0,"name":"Shaded","section":"Shading Mode"},"sceneLighting":true,"audioPlay":false,"sceneViewState":{"m_AlwaysRefresh":false,"showFog":true,"showSkybox":true,"showFlares":true,"showImageEffects":true,"showParticleSystems":true,"showVisualEffectGraphs":true,"m_FxEnabled":true},"in2DMode":false,"pivot":{"x":462.1152648925781,"y":188.7960662841797,"z":-9.970062255859375},"rotation":{"x":0.12731771171092988,"y":0.026676099747419359,"z":-0.0031987724360078575,"w":0.9915525317192078},"size":261.0076599121094,"orthographic":false}